topsis_python/Topsis.py
TOPSIS_MAHESH_MANI_102297002-1.0.0.dist-info/LICENSE.txt
TOPSIS_MAHESH_MANI_102297002-1.0.0.dist-info/METADATA
TOPSIS_MAHESH_MANI_102297002-1.0.0.dist-info/WHEEL
TOPSIS_MAHESH_MANI_102297002-1.0.0.dist-info/entry_points.txt
TOPSIS_MAHESH_MANI_102297002-1.0.0.dist-info/top_level.txt
TOPSIS_MAHESH_MANI_102297002-1.0.0.dist-info/RECORD
