Metadata-Version: 2.1
Name: TOPSIS-MAHESH-MANI-102297002
Version: 1.0.0
Summary: A Python package to find TOPSIS for multi-criteria decision analysis method
Home-page: https://www.github.com/maheshmani13
Author: Mahesh Mani
Author-email: imaheshmani13@gmail.com
License: MIT
Keywords: topsis,UCS654,TIET
Classifier: Development Status :: 3 - Alpha
Classifier: Intended Audience :: Developers
Classifier: Operating System :: Microsoft :: Windows :: Windows 10
Classifier: Operating System :: MacOS :: MacOS X
Classifier: License :: OSI Approved :: MIT License
Classifier: Programming Language :: Python :: 3
License-File: LICENSE.txt
Requires-Dist: pandas
Requires-Dist: numpy
